django_ecommerce/__init__.py
django_ecommerce/admin.py
django_ecommerce/apps.py
django_ecommerce/context_processors.py
django_ecommerce/models.py
django_ecommerce/urls.py
django_ecommerce/utils.py
django_ecommerce/migrations/0001_initial.py
django_ecommerce/migrations/0002_category_seo_image_cropped_product_seo_image_cropped_and_more.py
django_ecommerce/migrations/0003_discount_last_activation_run_last_deactivation_run.py
django_ecommerce/migrations/__init__.py
django_ecommerce/templatetags/__init__.py
django_ecommerce/templatetags/ecommerce_filters.py
django_ecommerce/tests/__init__.py
django_ecommerce/tests/test_models.py
django_ecommerce/tests/test_utils.py
django_ecommerce-1.0.13.dist-info/licenses/LICENSE
django_ecommerce-1.0.13.dist-info/METADATA
django_ecommerce-1.0.13.dist-info/WHEEL
django_ecommerce-1.0.13.dist-info/top_level.txt
django_ecommerce-1.0.13.dist-info/RECORD
