Metadata-Version: 2.4
Name: django-ecommerce
Version: 1.0.13
Summary: A Django E-commerce app for streamlined online retail, featuring product management, order processing, and flexible settings for discounts and stock tracking.
Author-email: cybermeh <cybermeh@icloud.com>
Classifier: Environment :: Web Environment
Classifier: Framework :: Django
Classifier: Framework :: Django :: 4.2
Classifier: Intended Audience :: Developers
Classifier: License :: OSI Approved :: BSD License
Classifier: Operating System :: OS Independent
Classifier: Programming Language :: Python
Classifier: Programming Language :: Python :: 3
Classifier: Programming Language :: Python :: 3 :: Only
Classifier: Programming Language :: Python :: 3.8
Classifier: Programming Language :: Python :: 3.9
Classifier: Topic :: Internet :: WWW/HTTP
Classifier: Topic :: Internet :: WWW/HTTP :: Dynamic Content
Requires-Python: >=3.10
License-File: LICENSE
Requires-Dist: django>=4.2
Requires-Dist: django-autoslug>=1.9.9
Requires-Dist: django-cloud-thumbnails>=1.2.2
Requires-Dist: django-money>=3.4.1
Requires-Dist: django-solo>=2.1.0
Requires-Dist: django-admin-sortable2>=2.1.10
Requires-Dist: pytz>=2023.3.post1
Dynamic: license-file
